Workbook
Name aporte: base!$D$16
Name patrimonio: base!$D$19
Name qtd_anos: base!$D$17
Name rendimento_carteira: base!$D$12
Name salario: base!$D$11
Name sugestao_investimento: base!$D$13
Name taxa_mensal: base!$D$18

Sheet base
B10: PARÂMETROS
B11: Salário | D11: 1500
B12: Rendimento Carteira | D12: 0.008
B13: Sugestão de Investimento (30%) | D13: =D11*30% -> 450
B15: INVESTIMENTO MENSAL
B16: Investimento Mensal | D16: 350
B17: Investimento Anual em Meses | D17: 12
B18: Taxa de Rendimento Anual | D18: 0.01079
B19: Patrimônio Acumulado | D19: =FV(taxa_mensal,qtd_anos*12,aporte*-1) -> 119694.88
B20: Dividendos Mensais | D20: =patrimonio*rendimento_carteira -> 957.55901
B22: Cenários | D22: Dividendo
A23: 2 | B23: 2 Anos | C23: =FV($D$18,$A23*12,$D$16*-1) -> 9529.6696 | D23: =C23*rendimento_carteira -> 76.237356
A24: 5 | B24: 5 Anos | C24: =FV($D$18,$A24*12,$D$16*-1) -> 29321.92 | D24: =C24*rendimento_carteira -> 234.57536
A25: 10 | B25: 10 Anos | C25: =FV($D$18,$A25*12,$D$16*-1) -> 85149.474 | D25: =C25*rendimento_carteira -> 681.1958
A26: 20 | B26: 20 Anos | C26: =FV($D$18,$A26*12,$D$16*-1) -> 393819.44 | D26: =C26*rendimento_carteira -> 3150.5555
A27: 30 | B27: 30 Anos | C27: =FV($D$18,$A27*12,$D$16*-1) -> 1512759.4 | D27: =C27*rendimento_carteira -> 12102.075
C30: Selecione o perfil do investidor
B31: PERFIL | C31: Conservador
B32: VALOR A SER INVESTIDO MENSALMENTE | C32: =aporte -> 350
B34: TIPO DE FII | C34: Percentual Sugerido | D34: Valores
B35: PAPEL | C35: =VLOOKUP($C$31&"-"&B35,tbl_FII!$B:$E,4,FALSE) -> 0.3 | D35: =C35*$C$32 -> 105
B36: TIJOLO | C36: =VLOOKUP($C$31&"-"&B36,tbl_FII!$B:$E,4,FALSE) -> 0.5 | D36: =C36*$C$32 -> 175
B37: HÍBRIDOS | C37: =VLOOKUP($C$31&"-"&B37,tbl_FII!$B:$E,4,FALSE) -> 0.1 | D37: =C37*$C$32 -> 35
B38: FOFs | C38: =VLOOKUP($C$31&"-"&B38,tbl_FII!$B:$E,4,FALSE) -> 0.1 | D38: =C38*$C$32 -> 35
B39: DESENVOLVIMENTO | C39: =VLOOKUP($C$31&"-"&B39,tbl_FII!$B:$E,4,FALSE) -> 0 | D39: =C39*$C$32 -> 0
B40: HOTELARIAS | C40: =VLOOKUP($C$31&"-"&B40,tbl_FII!$B:$E,4,FALSE) -> 0 | D40: =C40*$C$32 -> 0
D41: =SUM(D35:D40) -> 350

Sheet tbl_FII
B2: CHAVE | C2: PERFIL | D2: TIPO DE FII | E2: %
B3: =C3&"-"&D3 -> Agressivo-PAPEL | C3: Agressivo | D3: PAPEL | E3: 0.5 | H3: %
B4: =C4&"-"&D4 -> Agressivo-TIJOLO | C4: Agressivo | D4: TIJOLO | E4: 0.1 | H4: Moderado-TIJOLO | I4: =VLOOKUP(H4,$B:$E,4,FALSE) -> 0.35
B5: =C5&"-"&D5 -> Agressivo-HÍBRIDOS | C5: Agressivo | D5: HÍBRIDOS | E5: 0.05
B6: =C6&"-"&D6 -> Agressivo-FOFs | C6: Agressivo | D6: FOFs | E6: 0.05
B7: =C7&"-"&D7 -> Agressivo-DESENVOLVIMENTO | C7: Agressivo | D7: DESENVOLVIMENTO | E7: 0.2
B8: =C8&"-"&D8 -> Agressivo-HOTELARIAS | C8: Agressivo | D8: HOTELARIAS | E8: 0.1
B9: =C9&"-"&D9 -> Conservador-PAPEL | C9: Conservador | D9: PAPEL | E9: 0.3
B10: =C10&"-"&D10 -> Conservador-TIJOLO | C10: Conservador | D10: TIJOLO | E10: 0.5
B11: =C11&"-"&D11 -> Conservador-HÍBRIDOS | C11: Conservador | D11: HÍBRIDOS | E11: 0.1
B12: =C12&"-"&D12 -> Conservador-FOFs | C12: Conservador | D12: FOFs | E12: 0.1
B13: =C13&"-"&D13 -> Conservador-DESENVOLVIMENTO | C13: Conservador | D13: DESENVOLVIMENTO | E13: 0
B14: =C14&"-"&D14 -> Conservador-HOTELARIAS | C14: Conservador | D14: HOTELARIAS | E14: 0
B15: =C15&"-"&D15 -> Moderado-PAPEL | C15: Moderado | D15: PAPEL | E15: 0.32
B16: =C16&"-"&D16 -> Moderado-TIJOLO | C16: Moderado | D16: TIJOLO | E16: 0.35
... B20: =C20&"-"&D20 -> Moderado-HOTELARIAS | C20: Moderado | D20: HOTELARIAS | E20: 0.1
